{
  "sourceLanguage": "en",
  "strings": {
    "about_dev_contact": {
      "localizations": {
        "en": {
          "stringUnit": {
            "state": "translated",
            "value": "Contact the developer"
          }
        },
        "es": {
          "stringUnit": {
            "state": "translated",
            "value": "Contactar al desarrollador"
          }
        }
      }
    },
    "about_footer_version": {
      "localizations": {
        "en": {
          "stringUnit": {
            "state": "translated",
            "value": "%1$@ %2$@"
          }
        },
        "es": {
          "stringUnit": {
            "state": "translated",
            "value": "%1$@ %2$@"
          }
        }
      }
    },
    "about_rate_app": {
      "localizations": {
        "en": {
          "stringUnit": {
            "state": "translated",
            "value": "Rate the application"
          }
        },
        "es": {
          "stringUnit": {
            "state": "translated",
            "value": "Calificar la aplicación"
          }
        }
      }
    },
    "about_section_label": {
      "localizations": {
        "en": {
          "stringUnit": {
            "state": "translated",
            "value": "About this"
          }
        },
        "es": {
          "stringUnit": {
            "state": "translated",
            "value": "Acerca de"
          }
        }
      }
    },
    "about_share_app": {
      "localizations": {
        "en": {
          "stringUnit": {
            "state": "translated",
            "value": "Share this app"
          }
        },
        "es": {
          "stringUnit": {
            "state": "translated",
            "value": "Compartir la aplicación"
          }
        }
      }
    }
  },
  "version": "1.0"
}